{
  "model_scaling_fedavg": [
    {
      "seed": 71,
      "accuracy": 0.1,
      "worst_class_accuracy": 0.0,
      "attack_success_rate": 0.0
    }
  ],
  "model_scaling_norm_clip": [
    {
      "seed": 71,
      "accuracy": 0.6844,
      "worst_class_accuracy": 0.285,
      "attack_success_rate": 0.9717777777777777
    }
  ],
  "backdoor_pixel_fedavg": [
    {
      "seed": 71,
      "accuracy": 0.7515,
      "worst_class_accuracy": 0.504,
      "attack_success_rate": 0.8328888888888889
    }
  ],
  "backdoor_pixel_norm_clip": [
    {
      "seed": 71,
      "accuracy": 0.7515,
      "worst_class_accuracy": 0.504,
      "attack_success_rate": 0.8328888888888889
    }
  ]
}